tests/__init__.py
tests/test_examples.py
tests/test_keepinframe_tag.py
trml2pdf/__init__.py
trml2pdf/color.py
trml2pdf/trml2pdf.py
trml2pdf/utils.py
trml2pdf-0.4.3.dist-info/DESCRIPTION.rst
trml2pdf-0.4.3.dist-info/METADATA
trml2pdf-0.4.3.dist-info/RECORD
trml2pdf-0.4.3.dist-info/WHEEL
trml2pdf-0.4.3.dist-info/entry_points.txt
trml2pdf-0.4.3.dist-info/metadata.json
trml2pdf-0.4.3.dist-info/top_level.txt
