Metadata-Version: 2.0
Name: trml2pdf
Version: 0.4.3
Summary: Tiny RML2PDF is a tool to easily create PDF document using special HTML-like markup language. 
Requires-Dist: reportlab (>=3.2.0)
Requires-Dist: six (>=1.9.0)
